{
  "id": "17231819975703976331",
  "slug": "playa-el-yaque-posada-yaque-sol-c-a",
  "url": "https://estei.app/stay/17231819975703976331/profile",
  "scrapedAt": "2026-04-14T16:27:51.289Z",
  "titulo": "Playa El Yaque Posada Yaque Sol, C.A",
  "descripcion": "Posada Yaque Sol, cuenta con 12 cómodas habitaciones; algunas ubicadas en planta baja y otras en planta alta, están equipadas con baño privado, ducha de agua caliente, aire acondicionado, ventilador de techo, nevera ejecutiva, Tv LED con onn y FireTV, terraza con hamaca y sillas. La Posada está ro...\n\nMostrar más",
  "tipoPropiedad": "APARTAMENTO",
  "precioPorNoche": 68,
  "precioOriginal": "$68 USD",
  "moneda": "USD",
  "capacidadMaxima": 2,
  "habitaciones": null,
  "banos": 1,
  "camas": 1,
  "direccion": "V2XP+QQG, El Yaque 6320, Nueva Esparta, Venezuela",
  "ciudad": "",
  "estado": "",
  "latitud": null,
  "longitud": null,
  "reglas": null,
  "politicaCancelacion": "",
  "horarioCheckIn": "10:00",
  "horarioCheckOut": "18:00",
  "estanciaMinima": 1,
  "estanciaMaxima": 365,
  "amenidades": [
    "Pet Friendly",
    "Aire acondicionado",
    "Ventilador",
    "Agua caliente",
    "Patio",
    "Estacionamiento",
    "Terraza",
    "Seguridad",
    "Servicios de streaming",
    "Piscina",
    "WiFi",
    "Cocina equipada",
    "Tanque de agua",
    "Copas",
    "Vajilla",
    "Juego de cubiertos",
    "Nevera",
    "Vasos",
    "TV",
    "Mesa de comedor",
    "Parrillera",
    "Tostadora",
    "Cafetera",
    "Licuadora",
    "Horno",
    "Juego de ollas",
    "Microondas",
    "Horarios",
    "Check-in:",
    "10:00 - 20:00",
    "Check-out:",
    "18:00 - 19:00",
    "Selecciona tu habitación",
    "Matrimonial",
    "1 Aire acondicionado",
    "4 Almohadas",
    "1 Baño privado",
    "1 Cama matrimonial",
    "Ver más información",
    "$68 /noche",
    "Capacidad para 2 viajeros",
    "Seleccionar",
    "Triple",
    "1 Aire acondicionado",
    "6 Almohadas",
    "1 Baño privado",
    "1 Cama matrimonial",
    "Ver más información",
    "$78 /noche",
    "Capacidad para 4 viajeros",
    "Seleccionar",
    "Cuadruple",
    "1 Aire acondicionado",
    "8 Almohadas",
    "1 Baño privado",
    "1 Cama matrimonial",
    "Ver más información",
    "$85 /noche",
    "Capacidad para 4 viajeros",
    "Seleccionar",
    "Quintuple",
    "1 Aire acondicionado",
    "10 Almohadas",
    "1 Baño privado",
    "1 Cama matrimonial",
    "Ver más información",
    "$98 /noche",
    "Capacidad para 5 viajeros",
    "Seleccionar",
    "Sextuple",
    "2 Aire acondicionado",
    "3 Cama queen",
    "12 Almohadas",
    "2 Baño privado",
    "Ver más información",
    "$126 /noche",
    "Capacidad para 6 viajeros",
    "Seleccionar",
    "Septuple",
    "2 Aire acondicionado",
    "12 Almohadas",
    "2 Baño privado",
    "2 Cama matrimonial",
    "Ver más información",
    "$136 /noche",
    "Capacidad para 7 viajeros",
    "Seleccionar",
    "Disponibilidad",
    "Abril 2026",
    "Do",
    "Lu",
    "Ma",
    "Mi",
    "Ju",
    "Vi",
    "Sa",
    "10",
    "11",
    "12",
    "13",
    "14",
    "15",
    "16",
    "17",
    "18",
    "19",
    "20",
    "21",
    "22",
    "23",
    "24",
    "25",
    "26",
    "27",
    "28",
    "29",
    "30",
    "Mayo 2026",
    "Do",
    "Lu",
    "Ma",
    "Mi",
    "Ju",
    "Vi",
    "Sa",
    "10",
    "11",
    "12",
    "13",
    "14",
    "15",
    "16",
    "17",
    "18",
    "19",
    "20",
    "21",
    "22",
    "23",
    "24",
    "25",
    "26",
    "27",
    "28",
    "29",
    "30",
    "31",
    "Reiniciar fechas",
    "Servicios Adicionales",
    "Traslado Terrestre/Marítimo",
    "Precio único",
    "$ 20.00",
    "Alquiler De Vehículo",
    "Precio por día",
    "$ 35.00",
    "Conoce a tu anfitrión",
    "Rafael",
    "Anfitrión",
    "Reseñas",
    "Calificación",
    "Año siendo anfitrión",
    "Mensaje al anfitrión",
    "Rafael es anfitrión",
    "Ubicación",
    "V2XP+QQG, El Yaque 6320, Nueva Esparta, Venezuela",
    "Keyboard shortcuts",
    "Map data ©2026",
    "Terms",
    "Report a map error",
    "Políticas",
    "Política de cancelación",
    "Más información",
    "$68 - 136 (BCV)",
    "/ noche",
    "Check In",
    "Check Out",
    "Viajeros",
    "1 Viajero",
    "Reservación de habitación",
    "$0.00",
    "Servicio Estei",
    "$0.00",
    "Total (Impuestos incluidos)",
    "$0.00",
    "Solicitar Reserva",
    "Explora Estei",
    "Tus alojamientos",
    "Tus viajes",
    "Seguridad y confianza",
    "Conoce Estei",
    "Sobre nosotros",
    "Soporte",
    "Atención al Cliente",
    "Ayuda cercana",
    "Términos y condiciones",
    "Políticas de privacidad",
    "Redes Sociales",
    "© 2024 Estei y",
    "Avila Tek",
    ". Todos los derechos reservados",
    "Estei"
  ],
  "anfitrion": {
    "nombre": null,
    "imagen": null,
    "miembroDesde": null,
    "telefono": null,
    "email": null,
    "whatsapp": null
  },
  "imagenes": [
    {
      "url": "https://ik.imagekit.io/g6qb6s7be/H5hz3865rbw7Q5n4l0561597oRq5075MFpSqUbTrm7Lup8Vf4K.jpg",
      "alt": "playa-el-yaque-posada-yaque-sol-ca-0",
      "orden": 1,
      "esPrincipal": true,
      "archivoLocal": "img/img_1.jpg"
    },
    {
      "url": "https://ik.imagekit.io/g6qb6s7be/s4jz185U7iWr9384GOU8Q93kl6wE3w7pve2B0Z4J3D0zbQ100G.jpg",
      "alt": "playa-el-yaque-posada-yaque-sol-ca-1",
      "orden": 2,
      "esPrincipal": false,
      "archivoLocal": "img/img_2.jpg"
    },
    {
      "url": "https://ik.imagekit.io/g6qb6s7be/341h621Y3107l76kk1MNEI8X88dami3R71PKBcE0K3I0w67a68.jpg",
      "alt": "playa-el-yaque-posada-yaque-sol-ca-2",
      "orden": 3,
      "esPrincipal": false,
      "archivoLocal": "img/img_3.jpg"
    },
    {
      "url": "https://avilatek.sfo3.digitaloceanspaces.com/stg/1a2B93fco8Ty6gpSj7MgD8K2ctO6e6OA3oRp2X57w8jLSLBTX5.jpg",
      "alt": "playa-el-yaque-posada-yaque-sol-ca-3",
      "orden": 4,
      "esPrincipal": false,
      "archivoLocal": "img/img_4.jpg"
    },
    {
      "url": "https://ik.imagekit.io/g6qb6s7be/vhnx1CgRL7634hJC0cX851MfaNg0FknbB6WG03R1Ldn34XTe5H.jpg",
      "alt": "1774548462477430841",
      "orden": 5,
      "esPrincipal": false,
      "archivoLocal": "img/img_5.jpg"
    },
    {
      "url": "https://ik.imagekit.io/g6qb6s7be/E43SQu4y32S4G9104587Sm14U888484VmI5q406n72e68a4L70.jpg",
      "alt": "1772536388593161031",
      "orden": 6,
      "esPrincipal": false,
      "archivoLocal": "img/img_6.jpg"
    },
    {
      "url": "https://ik.imagekit.io/g6qb6s7be/nv4u6JZkOB4X9L233I1918110lu328g2L9rpLQ2lm8hL245J31.jpg",
      "alt": "1741292340999839699",
      "orden": 7,
      "esPrincipal": false,
      "archivoLocal": "img/img_7.jpg"
    }
  ]
}