{
  "id": "estei_1775520255894_3",
  "titulo": "Habitacin 1 Con Bao Compartido Para 2 Personas",
  "descripcion": "Habitación #1 con baño comparti...ApartamentoMiranda1 habitaciones disponibles4.67(BCV) $23 / noche",
  "tipoPropiedad": "HABITACION",
  "precioPorNoche": 23,
  "moneda": "USD",
  "capacidadMaxima": 2,
  "habitaciones": 1,
  "banos": 1,
  "camas": 1,
  "direccion": "",
  "ciudad": "Venezuela",
  "estado": "Distrito Capital",
  "zona": null,
  "latitud": null,
  "longitud": null,
  "reglas": null,
  "politicaCancelacion": "MODERADA",
  "horarioCheckIn": "15:00",
  "horarioCheckOut": "11:00",
  "estanciaMinima": 1,
  "estanciaMaxima": 30,
  "estadoPublicacion": "PUBLICADA",
  "imagenes": [
    {
      "url": "https://ik.imagekit.io/g6qb6s7be/D6C55EMJR2tNb2R8yN09e33DOZ5A0Rx1mV63i09fTbQ3QhefKK.jpg",
      "alt": "habitacin-1-con-bao-compartido-para-2-personas-0",
      "orden": 1,
      "esPrincipal": true
    }
  ],
  "amenidades": [
    "wifi",
    "aire_acondicionado"
  ],
  "fuenteScraping": {
    "sitio": "estei.app",
    "urlOriginal": "https://estei.app",
    "fechaScraping": "2026-04-07T00:04:15.894Z"
  }
}